{
    "last_run": "2026-04-19T00:40:03Z",
    "last_run_id": "24617397828",
    "monthly_activity_issue": {"month": "2026-04", "number": 494},
    "label_cursor": 494,
    "open_repo_assist_prs": [
        {"branch": "repo-assist/tests-generative-custom-attrs-20260419", "title": "tests: add GenerativeCustomAttributeTests; prepare release 8.7.0", "created": "2026-04-19"}
    ],
    "merged_this_month": [490, 491, 493, 495, 497, 498, 499, 501, 502, 504, 505],
    "comments_made": {
        "298": "2026-02-26", "299": "2026-02-26", "300": "2026-02-26", "384": "2026-02-26"
    },
    "notes": "PR #504 (GenerativePropertiesTests) and #505 (GenerativeMethodsTests) both merged. New PR branch repo-assist/tests-generative-custom-attrs-20260419 open: 5 new GenerativeCustomAttributeTests (attr on type/method, bool arg, enum arg, multiple attrs); 147/147 tests pass. RELEASE_NOTES updated to 8.7.0."
}
